Compiled from "Tuple.scala"
public abstract class perf.abs2.Tuple4$mcI$sp$class {
  public static java.lang.Object updateX(perf.abs2.Tuple4$mcI$sp, int);
    Code:
       0: aload_0       
       1: iload_1       
       2: invokeinterface #12,  2           // InterfaceMethod perf/abs2/Tuple4.updateX$mcI$sp:(I)Ljava/lang/Object;
       7: areturn       

  public static java.lang.Object updateY(perf.abs2.Tuple4$mcI$sp, int);
    Code:
       0: aload_0       
       1: iload_1       
       2: invokeinterface #21,  2           // InterfaceMethod perf/abs2/Tuple4.updateY$mcI$sp:(I)Ljava/lang/Object;
       7: areturn       

  public static java.lang.Object updateZ(perf.abs2.Tuple4$mcI$sp, int);
    Code:
       0: aload_0       
       1: iload_1       
       2: invokeinterface #25,  2           // InterfaceMethod perf/abs2/Tuple4.updateZ$mcI$sp:(I)Ljava/lang/Object;
       7: areturn       

  public static java.lang.Object updateW(perf.abs2.Tuple4$mcI$sp, int);
    Code:
       0: aload_0       
       1: iload_1       
       2: invokeinterface #29,  2           // InterfaceMethod perf/abs2/Tuple4.updateW$mcI$sp:(I)Ljava/lang/Object;
       7: areturn       

  public static void $init$(perf.abs2.Tuple4$mcI$sp);
    Code:
       0: return        
}
