Compiled from "Tuple.scala"
public abstract class perf.abs2.TupleAccess$class {
  public static double apply$mcD$sp(perf.abs2.TupleAccess, int);
    Code:
       0: aload_0       
       1: iload_1       
       2: invokeinterface #12,  2           // InterfaceMethod perf/abs2/TupleAccess.apply:(I)Ljava/lang/Object;
       7: invokestatic  #18                 // Method scala/runtime/BoxesRunTime.unboxToDouble:(Ljava/lang/Object;)D
      10: dreturn       

  public static int apply$mcI$sp(perf.abs2.TupleAccess, int);
    Code:
       0: aload_0       
       1: iload_1       
       2: invokeinterface #12,  2           // InterfaceMethod perf/abs2/TupleAccess.apply:(I)Ljava/lang/Object;
       7: invokestatic  #29                 // Method scala/runtime/BoxesRunTime.unboxToInt:(Ljava/lang/Object;)I
      10: ireturn       

  public static java.lang.Object update$mcD$sp(perf.abs2.TupleAccess, int, double);
    Code:
       0: aload_0       
       1: iload_1       
       2: dload_2       
       3: invokestatic  #35                 // Method scala/runtime/BoxesRunTime.boxToDouble:(D)Ljava/lang/Double;
       6: invokeinterface #39,  3           // InterfaceMethod perf/abs2/TupleAccess.update:(ILjava/lang/Object;)Ljava/lang/Object;
      11: areturn       

  public static java.lang.Object update$mcI$sp(perf.abs2.TupleAccess, int, int);
    Code:
       0: aload_0       
       1: iload_1       
       2: iload_2       
       3: invokestatic  #47                 // Method scala/runtime/BoxesRunTime.boxToInteger:(I)Ljava/lang/Integer;
       6: invokeinterface #39,  3           // InterfaceMethod perf/abs2/TupleAccess.update:(ILjava/lang/Object;)Ljava/lang/Object;
      11: areturn       

  public static void $init$(perf.abs2.TupleAccess);
    Code:
       0: return        
}
