Compiled from "Tuple.scala"
public abstract class perf.abs2.Tuple4$mcD$sp$class {
  public static java.lang.Object updateX(perf.abs2.Tuple4$mcD$sp, double);
    Code:
       0: aload_0       
       1: dload_1       
       2: invokeinterface #12,  3           // InterfaceMethod perf/abs2/Tuple4.updateX$mcD$sp:(D)Ljava/lang/Object;
       7: areturn       

  public static java.lang.Object updateY(perf.abs2.Tuple4$mcD$sp, double);
    Code:
       0: aload_0       
       1: dload_1       
       2: invokeinterface #21,  3           // InterfaceMethod perf/abs2/Tuple4.updateY$mcD$sp:(D)Ljava/lang/Object;
       7: areturn       

  public static java.lang.Object updateZ(perf.abs2.Tuple4$mcD$sp, double);
    Code:
       0: aload_0       
       1: dload_1       
       2: invokeinterface #25,  3           // InterfaceMethod perf/abs2/Tuple4.updateZ$mcD$sp:(D)Ljava/lang/Object;
       7: areturn       

  public static java.lang.Object updateW(perf.abs2.Tuple4$mcD$sp, double);
    Code:
       0: aload_0       
       1: dload_1       
       2: invokeinterface #29,  3           // InterfaceMethod perf/abs2/Tuple4.updateW$mcD$sp:(D)Ljava/lang/Object;
       7: areturn       

  public static void $init$(perf.abs2.Tuple4$mcD$sp);
    Code:
       0: return        
}
