Compiled from "VecNd.scala"
public final class perf.abs2.VecNd$$anonfun$$div$1 extends scala.runtime.AbstractFunction2$mcDDD$sp implements scala.Serializable {
  public static final long serialVersionUID;

  public static {};
    Code:
       0: lconst_0      
       1: lconst_0      
       2: putstatic     #11                 // Field serialVersionUID:J
       5: return        

  public final double apply(double, double);
    Code:
       0: aload_0       
       1: dload_1       
       2: dload_3       
       3: invokevirtual #17                 // Method apply$mcDDD$sp:(DD)D
       6: dreturn       

  public double apply$mcDDD$sp(double, double);
    Code:
       0: dload_1       
       1: dload_3       
       2: ddiv          
       3: dreturn       

  public final java.lang.Object apply(java.lang.Object, java.lang.Object);
    Code:
       0: aload_0       
       1: aload_1       
       2: invokestatic  #30                 // Method scala/runtime/BoxesRunTime.unboxToDouble:(Ljava/lang/Object;)D
       5: aload_2       
       6: invokestatic  #30                 // Method scala/runtime/BoxesRunTime.unboxToDouble:(Ljava/lang/Object;)D
       9: invokevirtual #32                 // Method apply:(DD)D
      12: invokestatic  #36                 // Method scala/runtime/BoxesRunTime.boxToDouble:(D)Ljava/lang/Double;
      15: areturn       

  public perf.abs2.VecNd$$anonfun$$div$1(perf.abs2.VecNd);
    Code:
       0: aload_0       
       1: invokespecial #43                 // Method scala/runtime/AbstractFunction2$mcDDD$sp."<init>":()V
       4: return        
}
