Compiled from "Benchmark.scala"
public final class perf.indirect.Benchmark {
  public static final perf.BenchUtil$Stats timeTest(java.lang.String, int, long, scala.Function0<java.lang.Object>);
    Code:
       0: getstatic     #11                 // Field perf/indirect/Benchmark$.MODULE$:Lperf/indirect/Benchmark$;
       3: aload_0       
       4: iload_1       
       5: lload_2       
       6: aload         4
       8: invokevirtual #13                 // Method perf/indirect/Benchmark$.timeTest:(Ljava/lang/String;IJLscala/Function0;)Lperf/BenchUtil$Stats;
      11: areturn       

  public static final void perf$BenchUtil$_setter_$iters_$eq(int);
    Code:
       0: getstatic     #11                 // Field perf/indirect/Benchmark$.MODULE$:Lperf/indirect/Benchmark$;
       3: iload_0       
       4: invokevirtual #19                 // Method perf/indirect/Benchmark$.perf$BenchUtil$_setter_$iters_$eq:(I)V
       7: return        

  public static final void perf$BenchUtil$_setter_$size_$eq(int);
    Code:
       0: getstatic     #11                 // Field perf/indirect/Benchmark$.MODULE$:Lperf/indirect/Benchmark$;
       3: iload_0       
       4: invokevirtual #22                 // Method perf/indirect/Benchmark$.perf$BenchUtil$_setter_$size_$eq:(I)V
       7: return        

  public static final int iters();
    Code:
       0: getstatic     #11                 // Field perf/indirect/Benchmark$.MODULE$:Lperf/indirect/Benchmark$;
       3: invokevirtual #26                 // Method perf/indirect/Benchmark$.iters:()I
       6: ireturn       

  public static final int size();
    Code:
       0: getstatic     #11                 // Field perf/indirect/Benchmark$.MODULE$:Lperf/indirect/Benchmark$;
       3: invokevirtual #29                 // Method perf/indirect/Benchmark$.size:()I
       6: ireturn       

  public static final void main(java.lang.String[]);
    Code:
       0: getstatic     #11                 // Field perf/indirect/Benchmark$.MODULE$:Lperf/indirect/Benchmark$;
       3: aload_0       
       4: invokevirtual #33                 // Method perf/indirect/Benchmark$.main:([Ljava/lang/String;)V
       7: return        
}
