Compiled from "Benchmark.scala"
public final class perf.indirect.Benchmark$$anonfun$main$1$$anonfun$apply$mcD$sp$1 extends scala.runtime.AbstractFunction1$mcVI$sp implements scala.Serializable {
  public static final long serialVersionUID;

  public static {};
    Code:
       0: lconst_0      
       1: lconst_0      
       2: putstatic     #11                 // Field serialVersionUID:J
       5: return        

  public final void apply(int);
    Code:
       0: aload_0       
       1: iload_1       
       2: invokevirtual #21                 // Method apply$mcVI$sp:(I)V
       5: return        

  public void apply$mcVI$sp(int);
    Code:
       0: aload_0       
       1: getfield      #28                 // Field result$1:Lscala/runtime/ObjectRef;
       4: aload_0       
       5: getfield      #30                 // Field $outer:Lperf/indirect/Benchmark$$anonfun$main$1;
       8: getfield      #36                 // Field perf/indirect/Benchmark$$anonfun$main$1.vecA$1:[Lperf/indirect/Vec3d;
      11: iload_1       
      12: aaload        
      13: aload_0       
      14: getfield      #30                 // Field $outer:Lperf/indirect/Benchmark$$anonfun$main$1;
      17: getfield      #39                 // Field perf/indirect/Benchmark$$anonfun$main$1.vecB$1:[Lperf/indirect/Vec3d;
      20: iload_1       
      21: aaload        
      22: invokeinterface #45,  2           // InterfaceMethod perf/indirect/VecOps3d.cross:(Lperf/indirect/Tuple3;)Lperf/indirect/Tuple3;
      27: checkcast     #47                 // class perf/indirect/TupleOps3d
      30: aload_0       
      31: getfield      #30                 // Field $outer:Lperf/indirect/Benchmark$$anonfun$main$1;
      34: getfield      #39                 // Field perf/indirect/Benchmark$$anonfun$main$1.vecB$1:[Lperf/indirect/Vec3d;
      37: iload_1       
      38: aaload        
      39: aload_0       
      40: getfield      #30                 // Field $outer:Lperf/indirect/Benchmark$$anonfun$main$1;
      43: getfield      #50                 // Field perf/indirect/Benchmark$$anonfun$main$1.vecC$1:[Lperf/indirect/Vec3d;
      46: iload_1       
      47: aaload        
      48: invokeinterface #54,  2           // InterfaceMethod perf/indirect/VecOps3d.dot:(Lperf/indirect/Tuple3;)D
      53: invokeinterface #58,  3           // InterfaceMethod perf/indirect/TupleOps3d.$times:(D)Lperf/indirect/Tuple3;
      58: checkcast     #47                 // class perf/indirect/TupleOps3d
      61: aload_0       
      62: getfield      #30                 // Field $outer:Lperf/indirect/Benchmark$$anonfun$main$1;
      65: getfield      #36                 // Field perf/indirect/Benchmark$$anonfun$main$1.vecA$1:[Lperf/indirect/Vec3d;
      68: iload_1       
      69: aaload        
      70: aload_0       
      71: getfield      #30                 // Field $outer:Lperf/indirect/Benchmark$$anonfun$main$1;
      74: getfield      #39                 // Field perf/indirect/Benchmark$$anonfun$main$1.vecB$1:[Lperf/indirect/Vec3d;
      77: iload_1       
      78: aaload        
      79: invokeinterface #61,  2           // InterfaceMethod perf/indirect/TupleOps3d.$div:(Lperf/indirect/Tuple3;)Lperf/indirect/Tuple3;
      84: invokeinterface #64,  2           // InterfaceMethod perf/indirect/TupleOps3d.$minus:(Lperf/indirect/Tuple3;)Lperf/indirect/Tuple3;
      89: checkcast     #66                 // class perf/indirect/Vec3d
      92: putfield      #72                 // Field scala/runtime/ObjectRef.elem:Ljava/lang/Object;
      95: return        

  public final java.lang.Object apply(java.lang.Object);
    Code:
       0: aload_0       
       1: aload_1       
       2: invokestatic  #80                 // Method scala/runtime/BoxesRunTime.unboxToInt:(Ljava/lang/Object;)I
       5: invokevirtual #82                 // Method apply:(I)V
       8: getstatic     #88                 // Field scala/runtime/BoxedUnit.UNIT:Lscala/runtime/BoxedUnit;
      11: areturn       

  public perf.indirect.Benchmark$$anonfun$main$1$$anonfun$apply$mcD$sp$1(perf.indirect.Benchmark$$anonfun$main$1, scala.runtime.ObjectRef);
    Code:
       0: aload_1       
       1: ifnonnull     12
       4: new           #92                 // class java/lang/NullPointerException
       7: dup           
       8: invokespecial #94                 // Method java/lang/NullPointerException."<init>":()V
      11: athrow        
      12: aload_0       
      13: aload_1       
      14: putfield      #30                 // Field $outer:Lperf/indirect/Benchmark$$anonfun$main$1;
      17: aload_0       
      18: aload_2       
      19: putfield      #28                 // Field result$1:Lscala/runtime/ObjectRef;
      22: aload_0       
      23: invokespecial #97                 // Method scala/runtime/AbstractFunction1$mcVI$sp."<init>":()V
      26: return        
}
