Compiled from "Vec3d.scala"
public abstract class perf.indirect.TupleOps3$mcD$sp$class {
  public static perf.indirect.Tuple3 $plus(perf.indirect.TupleOps3$mcD$sp, double);
    Code:
       0: aload_0       
       1: dload_1       
       2: invokeinterface #12,  3           // InterfaceMethod perf/indirect/TupleOps3.$plus$mcD$sp:(D)Lperf/indirect/Tuple3;
       7: areturn       

  public static perf.indirect.Tuple3 $minus(perf.indirect.TupleOps3$mcD$sp, double);
    Code:
       0: aload_0       
       1: dload_1       
       2: invokeinterface #21,  3           // InterfaceMethod perf/indirect/TupleOps3.$minus$mcD$sp:(D)Lperf/indirect/Tuple3;
       7: areturn       

  public static perf.indirect.Tuple3 $times(perf.indirect.TupleOps3$mcD$sp, double);
    Code:
       0: aload_0       
       1: dload_1       
       2: invokeinterface #25,  3           // InterfaceMethod perf/indirect/TupleOps3.$times$mcD$sp:(D)Lperf/indirect/Tuple3;
       7: areturn       

  public static perf.indirect.Tuple3 $div(perf.indirect.TupleOps3$mcD$sp, double);
    Code:
       0: aload_0       
       1: dload_1       
       2: invokeinterface #29,  3           // InterfaceMethod perf/indirect/TupleOps3.$div$mcD$sp:(D)Lperf/indirect/Tuple3;
       7: areturn       

  public static double magSq(perf.indirect.TupleOps3$mcD$sp);
    Code:
       0: aload_0       
       1: invokeinterface #35,  1           // InterfaceMethod perf/indirect/TupleOps3.magSq$mcD$sp:()D
       6: dreturn       

  public static double mag(perf.indirect.TupleOps3$mcD$sp);
    Code:
       0: aload_0       
       1: invokeinterface #39,  1           // InterfaceMethod perf/indirect/TupleOps3.mag$mcD$sp:()D
       6: dreturn       

  public static double dot(perf.indirect.TupleOps3$mcD$sp, perf.indirect.Tuple3);
    Code:
       0: aload_0       
       1: aload_1       
       2: invokeinterface #45,  2           // InterfaceMethod perf/indirect/TupleOps3.dot$mcD$sp:(Lperf/indirect/Tuple3;)D
       7: dreturn       

  public static perf.indirect.Tuple3 map(perf.indirect.TupleOps3$mcD$sp, perf.indirect.Tuple3, scala.Function1);
    Code:
       0: aload_0       
       1: aload_1       
       2: aload_2       
       3: invokeinterface #53,  3           // InterfaceMethod perf/indirect/TupleOps3.map$mcD$sp:(Lperf/indirect/Tuple3;Lscala/Function1;)Lperf/indirect/Tuple3;
       8: areturn       

  public static double reduce(perf.indirect.TupleOps3$mcD$sp, scala.Function2);
    Code:
       0: aload_0       
       1: aload_1       
       2: invokeinterface #61,  2           // InterfaceMethod perf/indirect/TupleOps3.reduce$mcD$sp:(Lscala/Function2;)D
       7: dreturn       

  public static perf.indirect.Tuple3 compwise(perf.indirect.TupleOps3$mcD$sp, perf.indirect.Tuple3, scala.Function2);
    Code:
       0: aload_0       
       1: aload_1       
       2: aload_2       
       3: invokeinterface #68,  3           // InterfaceMethod perf/indirect/TupleOps3.compwise$mcD$sp:(Lperf/indirect/Tuple3;Lscala/Function2;)Lperf/indirect/Tuple3;
       8: areturn       

  public static void $init$(perf.indirect.TupleOps3$mcD$sp);
    Code:
       0: return        
}
