Compiled from "Benchmark.scala"
public class perf.concrete.Benchmark$Stats implements scala.ScalaObject {
  public long duration();
    Code:
       0: aload_0       
       1: getfield      #16                 // Field duration:J
       4: lreturn       

  public long ops();
    Code:
       0: aload_0       
       1: getfield      #18                 // Field ops:J
       4: lreturn       

  public double timeInSec();
    Code:
       0: aload_0       
       1: getfield      #21                 // Field timeInSec:D
       4: dreturn       

  public double timePerOp();
    Code:
       0: aload_0       
       1: getfield      #23                 // Field timePerOp:D
       4: dreturn       

  public long opsPerSec();
    Code:
       0: aload_0       
       1: getfield      #25                 // Field opsPerSec:J
       4: lreturn       

  public void report();
    Code:
       0: getstatic     #33                 // Field scala/Predef$.MODULE$:Lscala/Predef$;
       3: getstatic     #33                 // Field scala/Predef$.MODULE$:Lscala/Predef$;
       6: ldc           #35                 // String Total Time: %.2f sec
       8: invokevirtual #39                 // Method scala/Predef$.augmentString:(Ljava/lang/String;)Lscala/collection/immutable/StringOps;
      11: getstatic     #33                 // Field scala/Predef$.MODULE$:Lscala/Predef$;
      14: iconst_1      
      15: anewarray     #41                 // class java/lang/Object
      18: dup           
      19: iconst_0      
      20: aload_0       
      21: invokevirtual #43                 // Method timeInSec:()D
      24: invokestatic  #49                 // Method scala/runtime/BoxesRunTime.boxToDouble:(D)Ljava/lang/Double;
      27: aastore       
      28: invokevirtual #53                 // Method scala/Predef$.genericWrapArray:(Ljava/lang/Object;)Lscala/collection/mutable/WrappedArray;
      31: invokeinterface #59,  2           // InterfaceMethod scala/collection/immutable/StringLike.format:(Lscala/collection/Seq;)Ljava/lang/String;
      36: invokevirtual #63                 // Method scala/Predef$.println:(Ljava/lang/Object;)V
      39: getstatic     #33                 // Field scala/Predef$.MODULE$:Lscala/Predef$;
      42: new           #65                 // class scala/collection/mutable/StringBuilder
      45: dup           
      46: invokespecial #68                 // Method scala/collection/mutable/StringBuilder."<init>":()V
      49: ldc           #70                 // String  Total Ops: 
      51: invokevirtual #74                 // Method scala/collection/mutable/StringBuilder.append:(Ljava/lang/Object;)Lscala/collection/mutable/StringBuilder;
      54: aload_0       
      55: invokevirtual #76                 // Method ops:()J
      58: invokestatic  #80                 // Method scala/runtime/BoxesRunTime.boxToLong:(J)Ljava/lang/Long;
      61: invokevirtual #74                 // Method scala/collection/mutable/StringBuilder.append:(Ljava/lang/Object;)Lscala/collection/mutable/StringBuilder;
      64: invokevirtual #84                 // Method scala/collection/mutable/StringBuilder.toString:()Ljava/lang/String;
      67: invokevirtual #63                 // Method scala/Predef$.println:(Ljava/lang/Object;)V
      70: getstatic     #33                 // Field scala/Predef$.MODULE$:Lscala/Predef$;
      73: getstatic     #33                 // Field scala/Predef$.MODULE$:Lscala/Predef$;
      76: ldc           #86                 // String  Time / Op: %.8f ms
      78: invokevirtual #39                 // Method scala/Predef$.augmentString:(Ljava/lang/String;)Lscala/collection/immutable/StringOps;
      81: getstatic     #33                 // Field scala/Predef$.MODULE$:Lscala/Predef$;
      84: iconst_1      
      85: anewarray     #41                 // class java/lang/Object
      88: dup           
      89: iconst_0      
      90: aload_0       
      91: invokevirtual #88                 // Method timePerOp:()D
      94: invokestatic  #49                 // Method scala/runtime/BoxesRunTime.boxToDouble:(D)Ljava/lang/Double;
      97: aastore       
      98: invokevirtual #53                 // Method scala/Predef$.genericWrapArray:(Ljava/lang/Object;)Lscala/collection/mutable/WrappedArray;
     101: invokeinterface #59,  2           // InterfaceMethod scala/collection/immutable/StringLike.format:(Lscala/collection/Seq;)Ljava/lang/String;
     106: invokevirtual #63                 // Method scala/Predef$.println:(Ljava/lang/Object;)V
     109: getstatic     #33                 // Field scala/Predef$.MODULE$:Lscala/Predef$;
     112: new           #65                 // class scala/collection/mutable/StringBuilder
     115: dup           
     116: invokespecial #68                 // Method scala/collection/mutable/StringBuilder."<init>":()V
     119: ldc           #90                 // String  Ops / Sec: 
     121: invokevirtual #74                 // Method scala/collection/mutable/StringBuilder.append:(Ljava/lang/Object;)Lscala/collection/mutable/StringBuilder;
     124: aload_0       
     125: invokevirtual #92                 // Method opsPerSec:()J
     128: invokestatic  #80                 // Method scala/runtime/BoxesRunTime.boxToLong:(J)Ljava/lang/Long;
     131: invokevirtual #74                 // Method scala/collection/mutable/StringBuilder.append:(Ljava/lang/Object;)Lscala/collection/mutable/StringBuilder;
     134: invokevirtual #84                 // Method scala/collection/mutable/StringBuilder.toString:()Ljava/lang/String;
     137: invokevirtual #63                 // Method scala/Predef$.println:(Ljava/lang/Object;)V
     140: return        

  public void summary(java.lang.String);
    Code:
       0: getstatic     #33                 // Field scala/Predef$.MODULE$:Lscala/Predef$;
       3: getstatic     #33                 // Field scala/Predef$.MODULE$:Lscala/Predef$;
       6: ldc           #96                 // String %s (MOps/Sec): %.2f
       8: invokevirtual #39                 // Method scala/Predef$.augmentString:(Ljava/lang/String;)Lscala/collection/immutable/StringOps;
      11: getstatic     #33                 // Field scala/Predef$.MODULE$:Lscala/Predef$;
      14: iconst_2      
      15: anewarray     #41                 // class java/lang/Object
      18: dup           
      19: iconst_0      
      20: aload_1       
      21: aastore       
      22: dup           
      23: iconst_1      
      24: aload_0       
      25: invokevirtual #92                 // Method opsPerSec:()J
      28: l2d           
      29: ldc2_w        #97                 // double 1000000.0d
      32: ddiv          
      33: invokestatic  #49                 // Method scala/runtime/BoxesRunTime.boxToDouble:(D)Ljava/lang/Double;
      36: aastore       
      37: invokevirtual #53                 // Method scala/Predef$.genericWrapArray:(Ljava/lang/Object;)Lscala/collection/mutable/WrappedArray;
      40: invokeinterface #59,  2           // InterfaceMethod scala/collection/immutable/StringLike.format:(Lscala/collection/Seq;)Ljava/lang/String;
      45: invokevirtual #63                 // Method scala/Predef$.println:(Ljava/lang/Object;)V
      48: return        

  public perf.concrete.Benchmark$Stats $plus(perf.concrete.Benchmark$Stats);
    Code:
       0: new           #14                 // class perf/concrete/Benchmark$Stats
       3: dup           
       4: aload_0       
       5: invokevirtual #107                // Method duration:()J
       8: aload_1       
       9: invokevirtual #107                // Method duration:()J
      12: ladd          
      13: aload_0       
      14: invokevirtual #76                 // Method ops:()J
      17: aload_1       
      18: invokevirtual #76                 // Method ops:()J
      21: ladd          
      22: invokespecial #110                // Method "<init>":(JJ)V
      25: areturn       

  public perf.concrete.Benchmark$Stats(long, long);
    Code:
       0: aload_0       
       1: lload_1       
       2: putfield      #16                 // Field duration:J
       5: aload_0       
       6: lload_3       
       7: putfield      #18                 // Field ops:J
      10: aload_0       
      11: invokespecial #112                // Method java/lang/Object."<init>":()V
      14: aload_0       
      15: lload_1       
      16: l2d           
      17: ldc2_w        #113                // double 1000.0d
      20: ddiv          
      21: putfield      #21                 // Field timeInSec:D
      24: aload_0       
      25: lload_1       
      26: l2d           
      27: lload_3       
      28: l2d           
      29: ddiv          
      30: putfield      #23                 // Field timePerOp:D
      33: aload_0       
      34: lload_3       
      35: ldc2_w        #115                // long 1000l
      38: lmul          
      39: lload_1       
      40: ldiv          
      41: putfield      #25                 // Field opsPerSec:J
      44: return        
}
