Compiled from "Benchmark.scala"
public final class perf.concrete.Benchmark$$anonfun$10 extends scala.runtime.AbstractFunction0 implements scala.Serializable {
  public static final long serialVersionUID;

  public static {};
    Code:
       0: lconst_0      
       1: lconst_0      
       2: putstatic     #11                 // Field serialVersionUID:J
       5: return        

  public final perf.concrete.Vec3d apply();
    Code:
       0: getstatic     #19                 // Field perf/concrete/Vec3d$.MODULE$:Lperf/concrete/Vec3d$;
       3: invokevirtual #23                 // Method perf/concrete/Vec3d$.random:()Lperf/concrete/Vec3d;
       6: areturn       

  public final java.lang.Object apply();
    Code:
       0: aload_0       
       1: invokevirtual #26                 // Method apply:()Lperf/concrete/Vec3d;
       4: areturn       

  public perf.concrete.Benchmark$$anonfun$10();
    Code:
       0: aload_0       
       1: invokespecial #31                 // Method scala/runtime/AbstractFunction0."<init>":()V
       4: return        
}
